webiks_hebrew_ragbot/__init__.py
webiks_hebrew_ragbot/config.py
webiks_hebrew_ragbot/document.py
webiks_hebrew_ragbot/elastic_model.py
webiks_hebrew_ragbot/engine.py
webiks_hebrew_ragbot/llm_client.py
webiks_hebrew_ragbot-1.4.0.dist-info/METADATA
webiks_hebrew_ragbot-1.4.0.dist-info/WHEEL
webiks_hebrew_ragbot-1.4.0.dist-info/top_level.txt
webiks_hebrew_ragbot-1.4.0.dist-info/RECORD
