Metadata-Version: 2.4
Name: webiks-hebrew-ragbot
Version: 1.4.0
Summary: A search engine using machine learning models and Elasticsearch for advanced document retrieval.
Home-page: https://github.com/shmuelrob/ragbot
Author: Shmuel Robinov
Author-email: shmuel_robinov@webiks.com
Classifier: Programming Language :: Python :: 3
Classifier: Operating System :: OS Independent
Requires-Python: >=3.10
Requires-Dist: elasticsearch==8.17.1
Requires-Dist: sentence-transformers==3.4.1
Requires-Dist: torch==2.6.0
Requires-Dist: transformers==4.48.3
Dynamic: author
Dynamic: author-email
Dynamic: classifier
Dynamic: description
Dynamic: description-content-type
Dynamic: home-page
Dynamic: requires-dist
Dynamic: requires-python
Dynamic: summary
